visorRobot/__init__.py
visorRobot/visor.py
visorRobot08-0.0.1.dist-info/METADATA
visorRobot08-0.0.1.dist-info/WHEEL
visorRobot08-0.0.1.dist-info/top_level.txt
visorRobot08-0.0.1.dist-info/RECORD
